[{"url":"http://asdfasdfasdfasdf.pl/368x338/?text=fake image 0"},{"url":"http://fakeimg.pl/413x205/?text=fake image 1"},{"url":"http://fakeimg.pl/433x212/?text=fake image 2"},{"url":"http://fakeimg.pl/328x199/?text=fake image 3"},{"url":"http://fakeimg.pl/234x191/?text=fake image 4"},{"url":"http://fakeimg.pl/275x298/?text=fake image 5"},{"url":"http://fakeimg.pl/346x209/?text=fake image 6"},{"url":"http://fakeimg.pl/336x309/?text=fake image 7"},{"url":"http://fakeimg.pl/353x303/?text=fake image 8"},{"url":"http://fakeimg.pl/397x223/?text=fake image 9"},{"url":"http://fakeimg.pl/200x165/?text=fake image 10"},{"url":"http://fakeimg.pl/351x304/?text=fake image 11"},{"url":"http://fakeimg.pl/425x177/?text=fake image 12"},{"url":"http://fakeimg.pl/248x169/?text=fake image 13"},{"url":"http://fakeimg.pl/250x238/?text=fake image 14"},{"url":"http://fakeimg.pl/293x306/?text=fake image 15"},{"url":"http://fakeimg.pl/271x333/?text=fake image 16"},{"url":"http://fakeimg.pl/298x350/?text=fake image 17"},{"url":"http://fakeimg.pl/258x305/?text=fake image 18"},{"url":"http://fakeimg.pl/312x191/?text=fake image 19"},{"url":"http://fakeimg.pl/378x248/?text=fake image 20"},{"url":"http://fakeimg.pl/246x278/?text=fake image 21"},{"url":"http://fakeimg.pl/283x175/?text=fake image 22"},{"url":"http://fakeimg.pl/316x181/?text=fake image 23"},{"url":"http://fakeimg.pl/273x277/?text=fake image 24"},{"url":"http://fakeimg.pl/439x256/?text=fake image 25"},{"url":"http://fakeimg.pl/204x228/?text=fake image 26"},{"url":"http://fakeimg.pl/277x337/?text=fake image 27"},{"url":"http://fakeimg.pl/223x321/?text=fake image 28"},{"url":"http://fakeimg.pl/381x301/?text=fake image 29"},{"url":"http://fakeimg.pl/244x250/?text=fake image 30"},{"url":"http://fakeimg.pl/374x265/?text=fake image 31"},{"url":"http://fakeimg.pl/499x349/?text=fake image 32"},{"url":"http://fakeimg.pl/213x295/?text=fake image 33"},{"url":"http://fakeimg.pl/279x203/?text=fake image 34"},{"url":"http://fakeimg.pl/262x178/?text=fake image 35"},{"url":"http://fakeimg.pl/324x322/?text=fake image 36"},{"url":"http://fakeimg.pl/350x168/?text=fake image 37"},{"url":"http://fakeimg.pl/356x298/?text=fake image 38"},{"url":"http://fakeimg.pl/434x251/?text=fake image 39"},{"url":"http://fakeimg.pl/480x188/?text=fake image 40"},{"url":"http://fakeimg.pl/269x261/?text=fake image 41"},{"url":"http://fakeimg.pl/466x236/?text=fake image 42"},{"url":"http://fakeimg.pl/360x305/?text=fake image 43"},{"url":"http://fakeimg.pl/384x337/?text=fake image 44"},{"url":"http://fakeimg.pl/337x293/?text=fake image 45"},{"url":"http://fakeimg.pl/436x222/?text=fake image 46"},{"url":"http://fakeimg.pl/495x187/?text=fake image 47"},{"url":"http://fakeimg.pl/337x358/?text=fake image 48"},{"url":"http://fakeimg.pl/287x258/?text=fake image 49"},{"url":"http://fakeimg.pl/475x261/?text=fake image 50"},{"url":"http://fakeimg.pl/250x200/?text=fake image 51"},{"url":"http://fakeimg.pl/274x304/?text=fake image 52"},{"url":"http://fakeimg.pl/322x307/?text=fake image 53"},{"url":"http://fakeimg.pl/224x237/?text=fake image 54"},{"url":"http://fakeimg.pl/435x270/?text=fake image 55"},{"url":"http://fakeimg.pl/374x186/?text=fake image 56"},{"url":"http://fakeimg.pl/323x216/?text=fake image 57"},{"url":"http://fakeimg.pl/474x180/?text=fake image 58"},{"url":"http://fakeimg.pl/447x246/?text=fake image 59"},{"url":"http://fakeimg.pl/206x200/?text=fake image 60"},{"url":"http://fakeimg.pl/245x328/?text=fake image 61"},{"url":"http://fakeimg.pl/315x161/?text=fake image 62"},{"url":"http://fakeimg.pl/444x307/?text=fake image 63"},{"url":"http://fakeimg.pl/271x202/?text=fake image 64"},{"url":"http://fakeimg.pl/447x209/?text=fake image 65"},{"url":"http://fakeimg.pl/414x226/?text=fake image 66"},{"url":"http://fakeimg.pl/368x358/?text=fake image 67"},{"url":"http://fakeimg.pl/457x317/?text=fake image 68"},{"url":"http://fakeimg.pl/266x170/?text=fake image 69"},{"url":"http://fakeimg.pl/225x269/?text=fake image 70"},{"url":"http://fakeimg.pl/221x263/?text=fake image 71"},{"url":"http://fakeimg.pl/224x232/?text=fake image 72"},{"url":"http://fakeimg.pl/302x322/?text=fake image 73"},{"url":"http://fakeimg.pl/465x348/?text=fake image 74"},{"url":"http://fakeimg.pl/343x272/?text=fake image 75"},{"url":"http://fakeimg.pl/344x239/?text=fake image 76"},{"url":"http://fakeimg.pl/412x313/?text=fake image 77"},{"url":"http://fakeimg.pl/417x289/?text=fake image 78"},{"url":"http://fakeimg.pl/254x243/?text=fake image 79"},{"url":"http://fakeimg.pl/340x311/?text=fake image 80"},{"url":"http://fakeimg.pl/487x264/?text=fake image 81"},{"url":"http://fakeimg.pl/437x179/?text=fake image 82"},{"url":"http://fakeimg.pl/397x207/?text=fake image 83"},{"url":"http://fakeimg.pl/470x170/?text=fake image 84"},{"url":"http://fakeimg.pl/205x236/?text=fake image 85"},{"url":"http://fakeimg.pl/347x247/?text=fake image 86"},{"url":"http://fakeimg.pl/280x257/?text=fake image 87"},{"url":"http://fakeimg.pl/386x284/?text=fake image 88"},{"url":"http://fakeimg.pl/391x281/?text=fake image 89"},{"url":"http://fakeimg.pl/234x194/?text=fake image 90"},{"url":"http://fakeimg.pl/447x184/?text=fake image 91"},{"url":"http://fakeimg.pl/365x310/?text=fake image 92"},{"url":"http://fakeimg.pl/356x301/?text=fake image 93"},{"url":"http://fakeimg.pl/493x338/?text=fake image 94"},{"url":"http://fakeimg.pl/359x288/?text=fake image 95"},{"url":"http://fakeimg.pl/276x304/?text=fake image 96"},{"url":"http://fakeimg.pl/268x352/?text=fake image 97"},{"url":"http://fakeimg.pl/317x276/?text=fake image 98"},{"url":"http://fakeimg.pl/404x331/?text=fake image 99"},{"url":"http://fakeimg.pl/491x235/?text=fake image 100"},{"url":"http://fakeimg.pl/252x251/?text=fake image 101"},{"url":"http://fakeimg.pl/231x291/?text=fake image 102"},{"url":"http://fakeimg.pl/246x251/?text=fake image 103"},{"url":"http://fakeimg.pl/465x180/?text=fake image 104"},{"url":"http://fakeimg.pl/392x325/?text=fake image 105"},{"url":"http://fakeimg.pl/449x282/?text=fake image 106"},{"url":"http://fakeimg.pl/258x325/?text=fake image 107"},{"url":"http://fakeimg.pl/325x219/?text=fake image 108"},{"url":"http://fakeimg.pl/487x294/?text=fake image 109"},{"url":"http://fakeimg.pl/235x278/?text=fake image 110"},{"url":"http://fakeimg.pl/287x231/?text=fake image 111"},{"url":"http://fakeimg.pl/259x191/?text=fake image 112"},{"url":"http://fakeimg.pl/467x204/?text=fake image 113"},{"url":"http://fakeimg.pl/290x209/?text=fake image 114"},{"url":"http://fakeimg.pl/440x318/?text=fake image 115"},{"url":"http://fakeimg.pl/284x193/?text=fake image 116"},{"url":"http://fakeimg.pl/459x160/?text=fake image 117"},{"url":"http://fakeimg.pl/201x284/?text=fake image 118"},{"url":"http://fakeimg.pl/279x184/?text=fake image 119"},{"url":"http://fakeimg.pl/298x253/?text=fake image 120"},{"url":"http://fakeimg.pl/467x165/?text=fake image 121"},{"url":"http://fakeimg.pl/406x213/?text=fake image 122"},{"url":"http://fakeimg.pl/329x192/?text=fake image 123"},{"url":"http://fakeimg.pl/257x198/?text=fake image 124"},{"url":"http://fakeimg.pl/270x182/?text=fake image 125"},{"url":"http://fakeimg.pl/395x168/?text=fake image 126"},{"url":"http://fakeimg.pl/268x216/?text=fake image 127"},{"url":"http://fakeimg.pl/259x300/?text=fake image 128"},{"url":"http://fakeimg.pl/361x174/?text=fake image 129"},{"url":"http://fakeimg.pl/226x184/?text=fake image 130"},{"url":"http://fakeimg.pl/422x255/?text=fake image 131"},{"url":"http://fakeimg.pl/346x303/?text=fake image 132"},{"url":"http://fakeimg.pl/314x161/?text=fake image 133"},{"url":"http://fakeimg.pl/411x293/?text=fake image 134"},{"url":"http://fakeimg.pl/457x173/?text=fake image 135"},{"url":"http://fakeimg.pl/357x219/?text=fake image 136"},{"url":"http://fakeimg.pl/366x299/?text=fake image 137"},{"url":"http://fakeimg.pl/394x332/?text=fake image 138"},{"url":"http://fakeimg.pl/392x206/?text=fake image 139"},{"url":"http://fakeimg.pl/330x305/?text=fake image 140"},{"url":"http://fakeimg.pl/343x247/?text=fake image 141"},{"url":"http://fakeimg.pl/353x302/?text=fake image 142"},{"url":"http://fakeimg.pl/309x329/?text=fake image 143"},{"url":"http://fakeimg.pl/449x258/?text=fake image 144"},{"url":"http://fakeimg.pl/263x171/?text=fake image 145"},{"url":"http://fakeimg.pl/380x297/?text=fake image 146"},{"url":"http://fakeimg.pl/399x229/?text=fake image 147"},{"url":"http://fakeimg.pl/259x238/?text=fake image 148"},{"url":"http://fakeimg.pl/244x292/?text=fake image 149"},{"url":"http://fakeimg.pl/426x339/?text=fake image 150"},{"url":"http://fakeimg.pl/224x342/?text=fake image 151"},{"url":"http://fakeimg.pl/400x195/?text=fake image 152"},{"url":"http://fakeimg.pl/206x315/?text=fake image 153"},{"url":"http://fakeimg.pl/448x264/?text=fake image 154"},{"url":"http://fakeimg.pl/330x340/?text=fake image 155"},{"url":"http://fakeimg.pl/212x313/?text=fake image 156"},{"url":"http://fakeimg.pl/346x201/?text=fake image 157"},{"url":"http://fakeimg.pl/336x277/?text=fake image 158"},{"url":"http://fakeimg.pl/301x172/?text=fake image 159"},{"url":"http://fakeimg.pl/465x269/?text=fake image 160"},{"url":"http://fakeimg.pl/206x201/?text=fake image 161"},{"url":"http://fakeimg.pl/398x349/?text=fake image 162"},{"url":"http://fakeimg.pl/319x163/?text=fake image 163"},{"url":"http://fakeimg.pl/397x170/?text=fake image 164"},{"url":"http://fakeimg.pl/273x316/?text=fake image 165"},{"url":"http://fakeimg.pl/439x187/?text=fake image 166"},{"url":"http://fakeimg.pl/445x306/?text=fake image 167"},{"url":"http://fakeimg.pl/275x289/?text=fake image 168"},{"url":"http://fakeimg.pl/428x179/?text=fake image 169"},{"url":"http://fakeimg.pl/406x210/?text=fake image 170"},{"url":"http://fakeimg.pl/212x217/?text=fake image 171"},{"url":"http://fakeimg.pl/268x349/?text=fake image 172"},{"url":"http://fakeimg.pl/463x179/?text=fake image 173"},{"url":"http://fakeimg.pl/360x189/?text=fake image 174"},{"url":"http://fakeimg.pl/277x219/?text=fake image 175"},{"url":"http://fakeimg.pl/200x230/?text=fake image 176"},{"url":"http://fakeimg.pl/230x219/?text=fake image 177"},{"url":"http://fakeimg.pl/252x254/?text=fake image 178"},{"url":"http://fakeimg.pl/278x239/?text=fake image 179"},{"url":"http://fakeimg.pl/313x301/?text=fake image 180"},{"url":"http://fakeimg.pl/425x164/?text=fake image 181"},{"url":"http://fakeimg.pl/470x168/?text=fake image 182"},{"url":"http://fakeimg.pl/247x168/?text=fake image 183"},{"url":"http://fakeimg.pl/361x304/?text=fake image 184"},{"url":"http://fakeimg.pl/362x170/?text=fake image 185"},{"url":"http://fakeimg.pl/355x188/?text=fake image 186"},{"url":"http://fakeimg.pl/388x346/?text=fake image 187"},{"url":"http://fakeimg.pl/363x231/?text=fake image 188"},{"url":"http://fakeimg.pl/487x215/?text=fake image 189"},{"url":"http://fakeimg.pl/452x200/?text=fake image 190"},{"url":"http://fakeimg.pl/429x176/?text=fake image 191"},{"url":"http://fakeimg.pl/326x244/?text=fake image 192"},{"url":"http://fakeimg.pl/380x332/?text=fake image 193"},{"url":"http://fakeimg.pl/472x246/?text=fake image 194"},{"url":"http://fakeimg.pl/395x333/?text=fake image 195"},{"url":"http://fakeimg.pl/383x292/?text=fake image 196"},{"url":"http://fakeimg.pl/266x273/?text=fake image 197"},{"url":"http://fakeimg.pl/221x270/?text=fake image 198"},{"url":"http://fakeimg.pl/425x176/?text=fake image 199"},{"url":"http://fakeimg.pl/205x333/?text=fake image 200"},{"url":"http://fakeimg.pl/238x338/?text=fake image 201"},{"url":"http://fakeimg.pl/221x258/?text=fake image 202"},{"url":"http://fakeimg.pl/414x236/?text=fake image 203"},{"url":"http://fakeimg.pl/452x270/?text=fake image 204"},{"url":"http://fakeimg.pl/441x172/?text=fake image 205"},{"url":"http://fakeimg.pl/455x223/?text=fake image 206"},{"url":"http://fakeimg.pl/304x283/?text=fake image 207"},{"url":"http://fakeimg.pl/321x226/?text=fake image 208"},{"url":"http://fakeimg.pl/388x177/?text=fake image 209"},{"url":"http://fakeimg.pl/314x303/?text=fake image 210"},{"url":"http://fakeimg.pl/437x343/?text=fake image 211"},{"url":"http://fakeimg.pl/441x160/?text=fake image 212"},{"url":"http://fakeimg.pl/439x232/?text=fake image 213"},{"url":"http://fakeimg.pl/364x354/?text=fake image 214"},{"url":"http://fakeimg.pl/474x340/?text=fake image 215"},{"url":"http://fakeimg.pl/235x262/?text=fake image 216"},{"url":"http://fakeimg.pl/322x249/?text=fake image 217"},{"url":"http://fakeimg.pl/329x224/?text=fake image 218"},{"url":"http://fakeimg.pl/296x162/?text=fake image 219"},{"url":"http://fakeimg.pl/247x193/?text=fake image 220"},{"url":"http://fakeimg.pl/488x274/?text=fake image 221"},{"url":"http://fakeimg.pl/308x236/?text=fake image 222"},{"url":"http://fakeimg.pl/351x249/?text=fake image 223"},{"url":"http://fakeimg.pl/259x230/?text=fake image 224"},{"url":"http://fakeimg.pl/494x280/?text=fake image 225"},{"url":"http://fakeimg.pl/265x247/?text=fake image 226"},{"url":"http://fakeimg.pl/387x331/?text=fake image 227"},{"url":"http://fakeimg.pl/492x307/?text=fake image 228"},{"url":"http://fakeimg.pl/276x295/?text=fake image 229"},{"url":"http://fakeimg.pl/330x182/?text=fake image 230"},{"url":"http://fakeimg.pl/360x328/?text=fake image 231"},{"url":"http://fakeimg.pl/234x194/?text=fake image 232"},{"url":"http://fakeimg.pl/408x214/?text=fake image 233"},{"url":"http://fakeimg.pl/324x161/?text=fake image 234"},{"url":"http://fakeimg.pl/268x311/?text=fake image 235"},{"url":"http://fakeimg.pl/348x245/?text=fake image 236"},{"url":"http://fakeimg.pl/471x230/?text=fake image 237"},{"url":"http://fakeimg.pl/398x275/?text=fake image 238"},{"url":"http://fakeimg.pl/498x273/?text=fake image 239"},{"url":"http://fakeimg.pl/437x237/?text=fake image 240"},{"url":"http://fakeimg.pl/283x267/?text=fake image 241"},{"url":"http://fakeimg.pl/386x304/?text=fake image 242"},{"url":"http://fakeimg.pl/364x247/?text=fake image 243"},{"url":"http://fakeimg.pl/276x286/?text=fake image 244"},{"url":"http://fakeimg.pl/390x320/?text=fake image 245"},{"url":"http://fakeimg.pl/307x302/?text=fake image 246"},{"url":"http://fakeimg.pl/477x226/?text=fake image 247"},{"url":"http://fakeimg.pl/301x324/?text=fake image 248"},{"url":"http://fakeimg.pl/323x229/?text=fake image 249"},{"url":"http://fakeimg.pl/341x319/?text=fake image 250"},{"url":"http://fakeimg.pl/237x327/?text=fake image 251"},{"url":"http://fakeimg.pl/492x273/?text=fake image 252"},{"url":"http://fakeimg.pl/330x214/?text=fake image 253"},{"url":"http://fakeimg.pl/282x225/?text=fake image 254"},{"url":"http://fakeimg.pl/407x289/?text=fake image 255"},{"url":"http://fakeimg.pl/231x328/?text=fake image 256"},{"url":"http://fakeimg.pl/498x358/?text=fake image 257"},{"url":"http://fakeimg.pl/209x205/?text=fake image 258"},{"url":"http://fakeimg.pl/263x226/?text=fake image 259"},{"url":"http://fakeimg.pl/314x317/?text=fake image 260"},{"url":"http://fakeimg.pl/250x223/?text=fake image 261"},{"url":"http://fakeimg.pl/210x199/?text=fake image 262"},{"url":"http://fakeimg.pl/485x296/?text=fake image 263"},{"url":"http://fakeimg.pl/498x172/?text=fake image 264"},{"url":"http://fakeimg.pl/428x310/?text=fake image 265"},{"url":"http://fakeimg.pl/237x227/?text=fake image 266"},{"url":"http://fakeimg.pl/388x264/?text=fake image 267"},{"url":"http://fakeimg.pl/424x325/?text=fake image 268"},{"url":"http://fakeimg.pl/381x291/?text=fake image 269"},{"url":"http://fakeimg.pl/248x333/?text=fake image 270"},{"url":"http://fakeimg.pl/276x348/?text=fake image 271"},{"url":"http://fakeimg.pl/254x165/?text=fake image 272"},{"url":"http://fakeimg.pl/348x174/?text=fake image 273"},{"url":"http://fakeimg.pl/482x334/?text=fake image 274"},{"url":"http://fakeimg.pl/478x160/?text=fake image 275"},{"url":"http://fakeimg.pl/386x222/?text=fake image 276"},{"url":"http://fakeimg.pl/437x253/?text=fake image 277"},{"url":"http://fakeimg.pl/210x193/?text=fake image 278"},{"url":"http://fakeimg.pl/309x270/?text=fake image 279"},{"url":"http://fakeimg.pl/397x182/?text=fake image 280"},{"url":"http://fakeimg.pl/248x269/?text=fake image 281"},{"url":"http://fakeimg.pl/204x350/?text=fake image 282"},{"url":"http://fakeimg.pl/356x254/?text=fake image 283"},{"url":"http://fakeimg.pl/304x261/?text=fake image 284"},{"url":"http://fakeimg.pl/378x326/?text=fake image 285"},{"url":"http://fakeimg.pl/496x250/?text=fake image 286"},{"url":"http://fakeimg.pl/456x171/?text=fake image 287"},{"url":"http://fakeimg.pl/318x330/?text=fake image 288"},{"url":"http://fakeimg.pl/429x181/?text=fake image 289"},{"url":"http://fakeimg.pl/201x326/?text=fake image 290"},{"url":"http://fakeimg.pl/467x285/?text=fake image 291"},{"url":"http://fakeimg.pl/377x258/?text=fake image 292"},{"url":"http://fakeimg.pl/473x236/?text=fake image 293"},{"url":"http://fakeimg.pl/291x234/?text=fake image 294"},{"url":"http://fakeimg.pl/246x178/?text=fake image 295"},{"url":"http://fakeimg.pl/484x345/?text=fake image 296"},{"url":"http://fakeimg.pl/460x272/?text=fake image 297"},{"url":"http://fakeimg.pl/259x212/?text=fake image 298"},{"url":"http://fakeimg.pl/475x234/?text=fake image 299"},{"url":"http://fakeimg.pl/456x340/?text=fake image 300"},{"url":"http://fakeimg.pl/445x224/?text=fake image 301"},{"url":"http://fakeimg.pl/426x301/?text=fake image 302"},{"url":"http://fakeimg.pl/212x287/?text=fake image 303"},{"url":"http://fakeimg.pl/429x231/?text=fake image 304"},{"url":"http://fakeimg.pl/372x169/?text=fake image 305"},{"url":"http://fakeimg.pl/207x212/?text=fake image 306"},{"url":"http://fakeimg.pl/306x196/?text=fake image 307"},{"url":"http://fakeimg.pl/213x179/?text=fake image 308"},{"url":"http://fakeimg.pl/411x161/?text=fake image 309"},{"url":"http://fakeimg.pl/230x274/?text=fake image 310"},{"url":"http://fakeimg.pl/438x286/?text=fake image 311"},{"url":"http://fakeimg.pl/210x246/?text=fake image 312"},{"url":"http://fakeimg.pl/460x343/?text=fake image 313"},{"url":"http://fakeimg.pl/202x200/?text=fake image 314"},{"url":"http://fakeimg.pl/344x208/?text=fake image 315"},{"url":"http://fakeimg.pl/257x252/?text=fake image 316"},{"url":"http://fakeimg.pl/468x191/?text=fake image 317"},{"url":"http://fakeimg.pl/321x269/?text=fake image 318"},{"url":"http://fakeimg.pl/285x222/?text=fake image 319"},{"url":"http://fakeimg.pl/393x217/?text=fake image 320"},{"url":"http://fakeimg.pl/331x190/?text=fake image 321"},{"url":"http://fakeimg.pl/314x327/?text=fake image 322"},{"url":"http://fakeimg.pl/351x320/?text=fake image 323"},{"url":"http://fakeimg.pl/244x209/?text=fake image 324"},{"url":"http://fakeimg.pl/434x357/?text=fake image 325"},{"url":"http://fakeimg.pl/407x343/?text=fake image 326"},{"url":"http://fakeimg.pl/244x355/?text=fake image 327"},{"url":"http://fakeimg.pl/314x193/?text=fake image 328"},{"url":"http://fakeimg.pl/446x181/?text=fake image 329"},{"url":"http://fakeimg.pl/241x214/?text=fake image 330"},{"url":"http://fakeimg.pl/395x220/?text=fake image 331"},{"url":"http://fakeimg.pl/435x237/?text=fake image 332"},{"url":"http://fakeimg.pl/348x161/?text=fake image 333"},{"url":"http://fakeimg.pl/291x274/?text=fake image 334"},{"url":"http://fakeimg.pl/262x302/?text=fake image 335"},{"url":"http://fakeimg.pl/216x198/?text=fake image 336"},{"url":"http://fakeimg.pl/480x320/?text=fake image 337"},{"url":"http://fakeimg.pl/426x349/?text=fake image 338"},{"url":"http://fakeimg.pl/315x246/?text=fake image 339"},{"url":"http://fakeimg.pl/237x249/?text=fake image 340"},{"url":"http://fakeimg.pl/461x245/?text=fake image 341"},{"url":"http://fakeimg.pl/206x244/?text=fake image 342"},{"url":"http://fakeimg.pl/298x168/?text=fake image 343"},{"url":"http://fakeimg.pl/410x184/?text=fake image 344"},{"url":"http://fakeimg.pl/246x216/?text=fake image 345"},{"url":"http://fakeimg.pl/398x359/?text=fake image 346"},{"url":"http://fakeimg.pl/317x298/?text=fake image 347"},{"url":"http://fakeimg.pl/476x260/?text=fake image 348"},{"url":"http://fakeimg.pl/496x306/?text=fake image 349"},{"url":"http://fakeimg.pl/254x216/?text=fake image 350"},{"url":"http://fakeimg.pl/405x343/?text=fake image 351"},{"url":"http://fakeimg.pl/279x327/?text=fake image 352"},{"url":"http://fakeimg.pl/220x224/?text=fake image 353"},{"url":"http://fakeimg.pl/400x261/?text=fake image 354"},{"url":"http://fakeimg.pl/293x342/?text=fake image 355"},{"url":"http://fakeimg.pl/205x278/?text=fake image 356"},{"url":"http://fakeimg.pl/325x195/?text=fake image 357"},{"url":"http://fakeimg.pl/367x329/?text=fake image 358"},{"url":"http://fakeimg.pl/204x264/?text=fake image 359"},{"url":"http://fakeimg.pl/286x264/?text=fake image 360"},{"url":"http://fakeimg.pl/288x290/?text=fake image 361"},{"url":"http://fakeimg.pl/464x359/?text=fake image 362"},{"url":"http://fakeimg.pl/481x190/?text=fake image 363"},{"url":"http://fakeimg.pl/429x256/?text=fake image 364"},{"url":"http://fakeimg.pl/431x301/?text=fake image 365"},{"url":"http://fakeimg.pl/282x221/?text=fake image 366"},{"url":"http://fakeimg.pl/397x203/?text=fake image 367"},{"url":"http://fakeimg.pl/213x345/?text=fake image 368"},{"url":"http://fakeimg.pl/348x328/?text=fake image 369"},{"url":"http://fakeimg.pl/295x196/?text=fake image 370"},{"url":"http://fakeimg.pl/282x255/?text=fake image 371"},{"url":"http://fakeimg.pl/499x250/?text=fake image 372"},{"url":"http://fakeimg.pl/413x237/?text=fake image 373"},{"url":"http://fakeimg.pl/379x345/?text=fake image 374"},{"url":"http://fakeimg.pl/316x215/?text=fake image 375"},{"url":"http://fakeimg.pl/252x330/?text=fake image 376"},{"url":"http://fakeimg.pl/262x300/?text=fake image 377"},{"url":"http://fakeimg.pl/292x295/?text=fake image 378"},{"url":"http://fakeimg.pl/226x199/?text=fake image 379"},{"url":"http://fakeimg.pl/372x241/?text=fake image 380"},{"url":"http://fakeimg.pl/436x346/?text=fake image 381"},{"url":"http://fakeimg.pl/495x276/?text=fake image 382"},{"url":"http://fakeimg.pl/469x262/?text=fake image 383"},{"url":"http://fakeimg.pl/274x329/?text=fake image 384"},{"url":"http://fakeimg.pl/273x339/?text=fake image 385"},{"url":"http://fakeimg.pl/266x327/?text=fake image 386"},{"url":"http://fakeimg.pl/341x286/?text=fake image 387"},{"url":"http://fakeimg.pl/330x165/?text=fake image 388"},{"url":"http://fakeimg.pl/289x218/?text=fake image 389"},{"url":"http://fakeimg.pl/359x210/?text=fake image 390"},{"url":"http://fakeimg.pl/260x209/?text=fake image 391"},{"url":"http://fakeimg.pl/232x177/?text=fake image 392"},{"url":"http://fakeimg.pl/367x214/?text=fake image 393"},{"url":"http://fakeimg.pl/475x174/?text=fake image 394"},{"url":"http://fakeimg.pl/309x346/?text=fake image 395"},{"url":"http://fakeimg.pl/479x168/?text=fake image 396"},{"url":"http://fakeimg.pl/444x187/?text=fake image 397"},{"url":"http://fakeimg.pl/407x311/?text=fake image 398"},{"url":"http://fakeimg.pl/439x201/?text=fake image 399"},{"url":"http://fakeimg.pl/473x237/?text=fake image 400"},{"url":"http://fakeimg.pl/398x341/?text=fake image 401"},{"url":"http://fakeimg.pl/251x279/?text=fake image 402"},{"url":"http://fakeimg.pl/390x296/?text=fake image 403"},{"url":"http://fakeimg.pl/202x172/?text=fake image 404"},{"url":"http://fakeimg.pl/348x181/?text=fake image 405"},{"url":"http://fakeimg.pl/222x348/?text=fake image 406"},{"url":"http://fakeimg.pl/494x336/?text=fake image 407"},{"url":"http://fakeimg.pl/492x330/?text=fake image 408"},{"url":"http://fakeimg.pl/210x354/?text=fake image 409"},{"url":"http://fakeimg.pl/267x293/?text=fake image 410"},{"url":"http://fakeimg.pl/267x189/?text=fake image 411"},{"url":"http://fakeimg.pl/345x234/?text=fake image 412"},{"url":"http://fakeimg.pl/317x222/?text=fake image 413"},{"url":"http://fakeimg.pl/468x202/?text=fake image 414"},{"url":"http://fakeimg.pl/465x236/?text=fake image 415"},{"url":"http://fakeimg.pl/490x221/?text=fake image 416"},{"url":"http://fakeimg.pl/248x228/?text=fake image 417"},{"url":"http://fakeimg.pl/404x326/?text=fake image 418"},{"url":"http://fakeimg.pl/434x352/?text=fake image 419"},{"url":"http://fakeimg.pl/295x317/?text=fake image 420"},{"url":"http://fakeimg.pl/282x194/?text=fake image 421"},{"url":"http://fakeimg.pl/430x304/?text=fake image 422"},{"url":"http://fakeimg.pl/292x319/?text=fake image 423"},{"url":"http://fakeimg.pl/219x253/?text=fake image 424"},{"url":"http://fakeimg.pl/252x338/?text=fake image 425"},{"url":"http://fakeimg.pl/304x248/?text=fake image 426"},{"url":"http://fakeimg.pl/419x222/?text=fake image 427"},{"url":"http://fakeimg.pl/481x355/?text=fake image 428"},{"url":"http://fakeimg.pl/300x347/?text=fake image 429"},{"url":"http://fakeimg.pl/324x268/?text=fake image 430"},{"url":"http://fakeimg.pl/493x286/?text=fake image 431"},{"url":"http://fakeimg.pl/335x328/?text=fake image 432"},{"url":"http://fakeimg.pl/321x356/?text=fake image 433"},{"url":"http://fakeimg.pl/296x318/?text=fake image 434"},{"url":"http://fakeimg.pl/352x251/?text=fake image 435"},{"url":"http://fakeimg.pl/402x265/?text=fake image 436"},{"url":"http://fakeimg.pl/395x239/?text=fake image 437"},{"url":"http://fakeimg.pl/464x199/?text=fake image 438"},{"url":"http://fakeimg.pl/359x288/?text=fake image 439"},{"url":"http://fakeimg.pl/204x171/?text=fake image 440"},{"url":"http://fakeimg.pl/261x295/?text=fake image 441"},{"url":"http://fakeimg.pl/283x164/?text=fake image 442"},{"url":"http://fakeimg.pl/306x207/?text=fake image 443"},{"url":"http://fakeimg.pl/404x358/?text=fake image 444"},{"url":"http://fakeimg.pl/452x359/?text=fake image 445"},{"url":"http://fakeimg.pl/283x317/?text=fake image 446"},{"url":"http://fakeimg.pl/328x228/?text=fake image 447"},{"url":"http://fakeimg.pl/402x343/?text=fake image 448"},{"url":"http://fakeimg.pl/252x238/?text=fake image 449"},{"url":"http://fakeimg.pl/399x232/?text=fake image 450"},{"url":"http://fakeimg.pl/221x339/?text=fake image 451"},{"url":"http://fakeimg.pl/293x171/?text=fake image 452"},{"url":"http://fakeimg.pl/233x296/?text=fake image 453"},{"url":"http://fakeimg.pl/493x225/?text=fake image 454"},{"url":"http://fakeimg.pl/425x348/?text=fake image 455"},{"url":"http://fakeimg.pl/483x347/?text=fake image 456"},{"url":"http://fakeimg.pl/340x214/?text=fake image 457"},{"url":"http://fakeimg.pl/431x349/?text=fake image 458"},{"url":"http://fakeimg.pl/240x303/?text=fake image 459"},{"url":"http://fakeimg.pl/201x329/?text=fake image 460"},{"url":"http://fakeimg.pl/236x334/?text=fake image 461"},{"url":"http://fakeimg.pl/334x193/?text=fake image 462"},{"url":"http://fakeimg.pl/291x293/?text=fake image 463"},{"url":"http://fakeimg.pl/399x287/?text=fake image 464"},{"url":"http://fakeimg.pl/496x301/?text=fake image 465"},{"url":"http://fakeimg.pl/319x296/?text=fake image 466"},{"url":"http://fakeimg.pl/433x205/?text=fake image 467"},{"url":"http://fakeimg.pl/382x209/?text=fake image 468"},{"url":"http://fakeimg.pl/305x176/?text=fake image 469"},{"url":"http://fakeimg.pl/470x272/?text=fake image 470"},{"url":"http://fakeimg.pl/411x277/?text=fake image 471"},{"url":"http://fakeimg.pl/480x276/?text=fake image 472"},{"url":"http://fakeimg.pl/207x222/?text=fake image 473"},{"url":"http://fakeimg.pl/265x283/?text=fake image 474"},{"url":"http://fakeimg.pl/282x254/?text=fake image 475"},{"url":"http://fakeimg.pl/215x165/?text=fake image 476"},{"url":"http://fakeimg.pl/256x202/?text=fake image 477"},{"url":"http://fakeimg.pl/339x187/?text=fake image 478"},{"url":"http://fakeimg.pl/429x238/?text=fake image 479"},{"url":"http://fakeimg.pl/299x279/?text=fake image 480"},{"url":"http://fakeimg.pl/203x222/?text=fake image 481"},{"url":"http://fakeimg.pl/277x187/?text=fake image 482"},{"url":"http://fakeimg.pl/300x169/?text=fake image 483"},{"url":"http://fakeimg.pl/314x201/?text=fake image 484"},{"url":"http://fakeimg.pl/207x208/?text=fake image 485"},{"url":"http://fakeimg.pl/415x232/?text=fake image 486"},{"url":"http://fakeimg.pl/375x313/?text=fake image 487"},{"url":"http://fakeimg.pl/437x277/?text=fake image 488"},{"url":"http://fakeimg.pl/210x209/?text=fake image 489"},{"url":"http://fakeimg.pl/362x278/?text=fake image 490"},{"url":"http://fakeimg.pl/306x216/?text=fake image 491"},{"url":"http://fakeimg.pl/269x267/?text=fake image 492"},{"url":"http://fakeimg.pl/310x286/?text=fake image 493"},{"url":"http://fakeimg.pl/227x264/?text=fake image 494"},{"url":"http://fakeimg.pl/289x336/?text=fake image 495"},{"url":"http://fakeimg.pl/393x172/?text=fake image 496"},{"url":"http://fakeimg.pl/250x214/?text=fake image 497"},{"url":"http://fakeimg.pl/250x197/?text=fake image 498"},{"url":"http://fakeimg.pl/267x358/?text=fake image 499"},{"url":"http://fakeimg.pl/248x225/?text=fake image 500"},{"url":"http://fakeimg.pl/384x244/?text=fake image 501"},{"url":"http://fakeimg.pl/409x240/?text=fake image 502"},{"url":"http://fakeimg.pl/263x197/?text=fake image 503"},{"url":"http://fakeimg.pl/239x259/?text=fake image 504"},{"url":"http://fakeimg.pl/475x174/?text=fake image 505"},{"url":"http://fakeimg.pl/330x305/?text=fake image 506"},{"url":"http://fakeimg.pl/306x243/?text=fake image 507"},{"url":"http://fakeimg.pl/356x188/?text=fake image 508"},{"url":"http://fakeimg.pl/457x320/?text=fake image 509"},{"url":"http://fakeimg.pl/207x181/?text=fake image 510"},{"url":"http://fakeimg.pl/419x323/?text=fake image 511"},{"url":"http://fakeimg.pl/422x336/?text=fake image 512"},{"url":"http://fakeimg.pl/387x295/?text=fake image 513"},{"url":"http://fakeimg.pl/494x186/?text=fake image 514"},{"url":"http://fakeimg.pl/212x348/?text=fake image 515"},{"url":"http://fakeimg.pl/429x217/?text=fake image 516"},{"url":"http://fakeimg.pl/316x289/?text=fake image 517"},{"url":"http://fakeimg.pl/471x275/?text=fake image 518"},{"url":"http://fakeimg.pl/439x191/?text=fake image 519"},{"url":"http://fakeimg.pl/377x249/?text=fake image 520"},{"url":"http://fakeimg.pl/283x294/?text=fake image 521"},{"url":"http://fakeimg.pl/341x342/?text=fake image 522"},{"url":"http://fakeimg.pl/396x209/?text=fake image 523"},{"url":"http://fakeimg.pl/437x171/?text=fake image 524"},{"url":"http://fakeimg.pl/244x244/?text=fake image 525"},{"url":"http://fakeimg.pl/398x277/?text=fake image 526"},{"url":"http://fakeimg.pl/327x306/?text=fake image 527"},{"url":"http://fakeimg.pl/409x325/?text=fake image 528"},{"url":"http://fakeimg.pl/267x317/?text=fake image 529"},{"url":"http://fakeimg.pl/471x345/?text=fake image 530"},{"url":"http://fakeimg.pl/365x298/?text=fake image 531"},{"url":"http://fakeimg.pl/219x189/?text=fake image 532"},{"url":"http://fakeimg.pl/328x211/?text=fake image 533"},{"url":"http://fakeimg.pl/384x329/?text=fake image 534"},{"url":"http://fakeimg.pl/420x175/?text=fake image 535"},{"url":"http://fakeimg.pl/473x311/?text=fake image 536"},{"url":"http://fakeimg.pl/377x170/?text=fake image 537"},{"url":"http://fakeimg.pl/423x302/?text=fake image 538"},{"url":"http://fakeimg.pl/358x291/?text=fake image 539"},{"url":"http://fakeimg.pl/316x265/?text=fake image 540"},{"url":"http://fakeimg.pl/499x199/?text=fake image 541"},{"url":"http://fakeimg.pl/490x287/?text=fake image 542"},{"url":"http://fakeimg.pl/321x215/?text=fake image 543"},{"url":"http://fakeimg.pl/423x175/?text=fake image 544"},{"url":"http://fakeimg.pl/335x272/?text=fake image 545"},{"url":"http://fakeimg.pl/314x273/?text=fake image 546"},{"url":"http://fakeimg.pl/366x160/?text=fake image 547"},{"url":"http://fakeimg.pl/445x242/?text=fake image 548"},{"url":"http://fakeimg.pl/434x301/?text=fake image 549"},{"url":"http://fakeimg.pl/489x269/?text=fake image 550"},{"url":"http://fakeimg.pl/330x225/?text=fake image 551"},{"url":"http://fakeimg.pl/223x203/?text=fake image 552"},{"url":"http://fakeimg.pl/448x338/?text=fake image 553"},{"url":"http://fakeimg.pl/276x294/?text=fake image 554"},{"url":"http://fakeimg.pl/310x160/?text=fake image 555"},{"url":"http://fakeimg.pl/480x277/?text=fake image 556"},{"url":"http://fakeimg.pl/358x303/?text=fake image 557"},{"url":"http://fakeimg.pl/483x228/?text=fake image 558"},{"url":"http://fakeimg.pl/343x235/?text=fake image 559"},{"url":"http://fakeimg.pl/429x315/?text=fake image 560"},{"url":"http://fakeimg.pl/381x282/?text=fake image 561"},{"url":"http://fakeimg.pl/388x173/?text=fake image 562"},{"url":"http://fakeimg.pl/491x312/?text=fake image 563"},{"url":"http://fakeimg.pl/471x343/?text=fake image 564"},{"url":"http://fakeimg.pl/401x286/?text=fake image 565"},{"url":"http://fakeimg.pl/322x175/?text=fake image 566"},{"url":"http://fakeimg.pl/404x330/?text=fake image 567"},{"url":"http://fakeimg.pl/347x181/?text=fake image 568"},{"url":"http://fakeimg.pl/301x313/?text=fake image 569"},{"url":"http://fakeimg.pl/417x160/?text=fake image 570"},{"url":"http://fakeimg.pl/208x265/?text=fake image 571"},{"url":"http://fakeimg.pl/467x240/?text=fake image 572"},{"url":"http://fakeimg.pl/205x211/?text=fake image 573"},{"url":"http://fakeimg.pl/209x220/?text=fake image 574"},{"url":"http://fakeimg.pl/279x278/?text=fake image 575"},{"url":"http://fakeimg.pl/283x221/?text=fake image 576"},{"url":"http://fakeimg.pl/363x237/?text=fake image 577"},{"url":"http://fakeimg.pl/255x274/?text=fake image 578"},{"url":"http://fakeimg.pl/429x221/?text=fake image 579"},{"url":"http://fakeimg.pl/226x264/?text=fake image 580"},{"url":"http://fakeimg.pl/496x300/?text=fake image 581"},{"url":"http://fakeimg.pl/289x161/?text=fake image 582"},{"url":"http://fakeimg.pl/258x326/?text=fake image 583"},{"url":"http://fakeimg.pl/321x314/?text=fake image 584"},{"url":"http://fakeimg.pl/269x185/?text=fake image 585"},{"url":"http://fakeimg.pl/208x258/?text=fake image 586"},{"url":"http://fakeimg.pl/343x254/?text=fake image 587"},{"url":"http://fakeimg.pl/303x334/?text=fake image 588"},{"url":"http://fakeimg.pl/409x336/?text=fake image 589"},{"url":"http://fakeimg.pl/349x175/?text=fake image 590"},{"url":"http://fakeimg.pl/404x222/?text=fake image 591"},{"url":"http://fakeimg.pl/333x184/?text=fake image 592"},{"url":"http://fakeimg.pl/284x199/?text=fake image 593"},{"url":"http://fakeimg.pl/468x166/?text=fake image 594"},{"url":"http://fakeimg.pl/208x265/?text=fake image 595"},{"url":"http://fakeimg.pl/455x188/?text=fake image 596"},{"url":"http://fakeimg.pl/424x327/?text=fake image 597"},{"url":"http://fakeimg.pl/431x334/?text=fake image 598"},{"url":"http://fakeimg.pl/380x309/?text=fake image 599"},{"url":"http://fakeimg.pl/435x235/?text=fake image 600"},{"url":"http://fakeimg.pl/452x315/?text=fake image 601"},{"url":"http://fakeimg.pl/499x238/?text=fake image 602"},{"url":"http://fakeimg.pl/316x196/?text=fake image 603"},{"url":"http://fakeimg.pl/275x342/?text=fake image 604"},{"url":"http://fakeimg.pl/403x239/?text=fake image 605"},{"url":"http://fakeimg.pl/200x206/?text=fake image 606"},{"url":"http://fakeimg.pl/342x247/?text=fake image 607"},{"url":"http://fakeimg.pl/468x305/?text=fake image 608"},{"url":"http://fakeimg.pl/255x335/?text=fake image 609"},{"url":"http://fakeimg.pl/316x335/?text=fake image 610"},{"url":"http://fakeimg.pl/383x303/?text=fake image 611"},{"url":"http://fakeimg.pl/412x179/?text=fake image 612"},{"url":"http://fakeimg.pl/485x256/?text=fake image 613"},{"url":"http://fakeimg.pl/480x324/?text=fake image 614"},{"url":"http://fakeimg.pl/392x239/?text=fake image 615"},{"url":"http://fakeimg.pl/249x278/?text=fake image 616"},{"url":"http://fakeimg.pl/398x208/?text=fake image 617"},{"url":"http://fakeimg.pl/313x255/?text=fake image 618"},{"url":"http://fakeimg.pl/417x329/?text=fake image 619"},{"url":"http://fakeimg.pl/241x254/?text=fake image 620"},{"url":"http://fakeimg.pl/341x248/?text=fake image 621"},{"url":"http://fakeimg.pl/272x196/?text=fake image 622"},{"url":"http://fakeimg.pl/207x313/?text=fake image 623"},{"url":"http://fakeimg.pl/298x208/?text=fake image 624"},{"url":"http://fakeimg.pl/392x230/?text=fake image 625"},{"url":"http://fakeimg.pl/465x173/?text=fake image 626"},{"url":"http://fakeimg.pl/342x257/?text=fake image 627"},{"url":"http://fakeimg.pl/491x232/?text=fake image 628"},{"url":"http://fakeimg.pl/226x358/?text=fake image 629"},{"url":"http://fakeimg.pl/363x271/?text=fake image 630"},{"url":"http://fakeimg.pl/422x173/?text=fake image 631"},{"url":"http://fakeimg.pl/378x285/?text=fake image 632"},{"url":"http://fakeimg.pl/316x231/?text=fake image 633"},{"url":"http://fakeimg.pl/445x197/?text=fake image 634"},{"url":"http://fakeimg.pl/448x250/?text=fake image 635"},{"url":"http://fakeimg.pl/464x162/?text=fake image 636"},{"url":"http://fakeimg.pl/262x290/?text=fake image 637"},{"url":"http://fakeimg.pl/214x324/?text=fake image 638"},{"url":"http://fakeimg.pl/273x215/?text=fake image 639"},{"url":"http://fakeimg.pl/381x223/?text=fake image 640"},{"url":"http://fakeimg.pl/238x228/?text=fake image 641"},{"url":"http://fakeimg.pl/429x163/?text=fake image 642"},{"url":"http://fakeimg.pl/329x342/?text=fake image 643"},{"url":"http://fakeimg.pl/297x273/?text=fake image 644"},{"url":"http://fakeimg.pl/241x201/?text=fake image 645"},{"url":"http://fakeimg.pl/307x316/?text=fake image 646"},{"url":"http://fakeimg.pl/405x210/?text=fake image 647"},{"url":"http://fakeimg.pl/249x173/?text=fake image 648"},{"url":"http://fakeimg.pl/322x165/?text=fake image 649"},{"url":"http://fakeimg.pl/261x264/?text=fake image 650"},{"url":"http://fakeimg.pl/347x241/?text=fake image 651"},{"url":"http://fakeimg.pl/224x237/?text=fake image 652"},{"url":"http://fakeimg.pl/360x257/?text=fake image 653"},{"url":"http://fakeimg.pl/200x329/?text=fake image 654"},{"url":"http://fakeimg.pl/206x281/?text=fake image 655"},{"url":"http://fakeimg.pl/448x184/?text=fake image 656"},{"url":"http://fakeimg.pl/221x165/?text=fake image 657"},{"url":"http://fakeimg.pl/379x311/?text=fake image 658"},{"url":"http://fakeimg.pl/412x175/?text=fake image 659"},{"url":"http://fakeimg.pl/444x253/?text=fake image 660"},{"url":"http://fakeimg.pl/464x255/?text=fake image 661"},{"url":"http://fakeimg.pl/311x337/?text=fake image 662"},{"url":"http://fakeimg.pl/419x193/?text=fake image 663"},{"url":"http://fakeimg.pl/234x282/?text=fake image 664"},{"url":"http://fakeimg.pl/483x261/?text=fake image 665"},{"url":"http://fakeimg.pl/453x302/?text=fake image 666"},{"url":"http://fakeimg.pl/298x228/?text=fake image 667"},{"url":"http://fakeimg.pl/339x229/?text=fake image 668"},{"url":"http://fakeimg.pl/302x226/?text=fake image 669"},{"url":"http://fakeimg.pl/207x249/?text=fake image 670"},{"url":"http://fakeimg.pl/256x307/?text=fake image 671"},{"url":"http://fakeimg.pl/374x190/?text=fake image 672"},{"url":"http://fakeimg.pl/493x223/?text=fake image 673"},{"url":"http://fakeimg.pl/252x285/?text=fake image 674"},{"url":"http://fakeimg.pl/429x185/?text=fake image 675"},{"url":"http://fakeimg.pl/375x221/?text=fake image 676"},{"url":"http://fakeimg.pl/314x300/?text=fake image 677"},{"url":"http://fakeimg.pl/232x223/?text=fake image 678"},{"url":"http://fakeimg.pl/462x345/?text=fake image 679"},{"url":"http://fakeimg.pl/478x197/?text=fake image 680"},{"url":"http://fakeimg.pl/301x359/?text=fake image 681"},{"url":"http://fakeimg.pl/298x173/?text=fake image 682"},{"url":"http://fakeimg.pl/410x258/?text=fake image 683"},{"url":"http://fakeimg.pl/429x227/?text=fake image 684"},{"url":"http://fakeimg.pl/204x306/?text=fake image 685"},{"url":"http://fakeimg.pl/303x234/?text=fake image 686"},{"url":"http://fakeimg.pl/426x198/?text=fake image 687"},{"url":"http://fakeimg.pl/357x226/?text=fake image 688"},{"url":"http://fakeimg.pl/351x223/?text=fake image 689"},{"url":"http://fakeimg.pl/365x174/?text=fake image 690"},{"url":"http://fakeimg.pl/295x350/?text=fake image 691"},{"url":"http://fakeimg.pl/438x322/?text=fake image 692"},{"url":"http://fakeimg.pl/449x197/?text=fake image 693"},{"url":"http://fakeimg.pl/453x311/?text=fake image 694"},{"url":"http://fakeimg.pl/298x223/?text=fake image 695"},{"url":"http://fakeimg.pl/396x276/?text=fake image 696"},{"url":"http://fakeimg.pl/229x331/?text=fake image 697"},{"url":"http://fakeimg.pl/202x293/?text=fake image 698"},{"url":"http://fakeimg.pl/432x321/?text=fake image 699"},{"url":"http://fakeimg.pl/277x302/?text=fake image 700"},{"url":"http://fakeimg.pl/458x268/?text=fake image 701"},{"url":"http://fakeimg.pl/486x305/?text=fake image 702"},{"url":"http://fakeimg.pl/378x355/?text=fake image 703"},{"url":"http://fakeimg.pl/208x314/?text=fake image 704"},{"url":"http://fakeimg.pl/391x198/?text=fake image 705"},{"url":"http://fakeimg.pl/205x217/?text=fake image 706"},{"url":"http://fakeimg.pl/442x251/?text=fake image 707"},{"url":"http://fakeimg.pl/248x166/?text=fake image 708"},{"url":"http://fakeimg.pl/213x267/?text=fake image 709"},{"url":"http://fakeimg.pl/385x253/?text=fake image 710"},{"url":"http://fakeimg.pl/331x228/?text=fake image 711"},{"url":"http://fakeimg.pl/216x323/?text=fake image 712"},{"url":"http://fakeimg.pl/314x221/?text=fake image 713"},{"url":"http://fakeimg.pl/210x217/?text=fake image 714"},{"url":"http://fakeimg.pl/236x323/?text=fake image 715"},{"url":"http://fakeimg.pl/491x315/?text=fake image 716"},{"url":"http://fakeimg.pl/390x190/?text=fake image 717"},{"url":"http://fakeimg.pl/220x305/?text=fake image 718"},{"url":"http://fakeimg.pl/275x274/?text=fake image 719"},{"url":"http://fakeimg.pl/234x187/?text=fake image 720"},{"url":"http://fakeimg.pl/447x161/?text=fake image 721"},{"url":"http://fakeimg.pl/422x359/?text=fake image 722"},{"url":"http://fakeimg.pl/315x252/?text=fake image 723"},{"url":"http://fakeimg.pl/490x339/?text=fake image 724"},{"url":"http://fakeimg.pl/446x179/?text=fake image 725"},{"url":"http://fakeimg.pl/490x317/?text=fake image 726"},{"url":"http://fakeimg.pl/486x197/?text=fake image 727"},{"url":"http://fakeimg.pl/361x239/?text=fake image 728"},{"url":"http://fakeimg.pl/462x212/?text=fake image 729"},{"url":"http://fakeimg.pl/204x220/?text=fake image 730"},{"url":"http://fakeimg.pl/340x290/?text=fake image 731"},{"url":"http://fakeimg.pl/458x227/?text=fake image 732"},{"url":"http://fakeimg.pl/314x238/?text=fake image 733"},{"url":"http://fakeimg.pl/293x202/?text=fake image 734"},{"url":"http://fakeimg.pl/314x173/?text=fake image 735"},{"url":"http://fakeimg.pl/291x359/?text=fake image 736"},{"url":"http://fakeimg.pl/203x344/?text=fake image 737"},{"url":"http://fakeimg.pl/225x257/?text=fake image 738"},{"url":"http://fakeimg.pl/445x236/?text=fake image 739"},{"url":"http://fakeimg.pl/305x341/?text=fake image 740"},{"url":"http://fakeimg.pl/255x275/?text=fake image 741"},{"url":"http://fakeimg.pl/316x357/?text=fake image 742"},{"url":"http://fakeimg.pl/205x350/?text=fake image 743"},{"url":"http://fakeimg.pl/380x275/?text=fake image 744"},{"url":"http://fakeimg.pl/222x333/?text=fake image 745"},{"url":"http://fakeimg.pl/473x185/?text=fake image 746"},{"url":"http://fakeimg.pl/392x186/?text=fake image 747"},{"url":"http://fakeimg.pl/281x180/?text=fake image 748"},{"url":"http://fakeimg.pl/203x346/?text=fake image 749"},{"url":"http://fakeimg.pl/207x342/?text=fake image 750"},{"url":"http://fakeimg.pl/329x341/?text=fake image 751"},{"url":"http://fakeimg.pl/338x243/?text=fake image 752"},{"url":"http://fakeimg.pl/416x247/?text=fake image 753"},{"url":"http://fakeimg.pl/245x192/?text=fake image 754"},{"url":"http://fakeimg.pl/312x169/?text=fake image 755"},{"url":"http://fakeimg.pl/380x205/?text=fake image 756"},{"url":"http://fakeimg.pl/277x249/?text=fake image 757"},{"url":"http://fakeimg.pl/259x296/?text=fake image 758"},{"url":"http://fakeimg.pl/353x356/?text=fake image 759"},{"url":"http://fakeimg.pl/273x181/?text=fake image 760"},{"url":"http://fakeimg.pl/476x242/?text=fake image 761"},{"url":"http://fakeimg.pl/277x334/?text=fake image 762"},{"url":"http://fakeimg.pl/210x221/?text=fake image 763"},{"url":"http://fakeimg.pl/402x177/?text=fake image 764"},{"url":"http://fakeimg.pl/381x343/?text=fake image 765"},{"url":"http://fakeimg.pl/300x242/?text=fake image 766"},{"url":"http://fakeimg.pl/218x330/?text=fake image 767"},{"url":"http://fakeimg.pl/215x175/?text=fake image 768"},{"url":"http://fakeimg.pl/248x307/?text=fake image 769"},{"url":"http://fakeimg.pl/497x320/?text=fake image 770"},{"url":"http://fakeimg.pl/352x348/?text=fake image 771"},{"url":"http://fakeimg.pl/331x325/?text=fake image 772"},{"url":"http://fakeimg.pl/379x235/?text=fake image 773"},{"url":"http://fakeimg.pl/289x299/?text=fake image 774"},{"url":"http://fakeimg.pl/224x248/?text=fake image 775"},{"url":"http://fakeimg.pl/480x289/?text=fake image 776"},{"url":"http://fakeimg.pl/310x351/?text=fake image 777"},{"url":"http://fakeimg.pl/433x303/?text=fake image 778"},{"url":"http://fakeimg.pl/351x339/?text=fake image 779"},{"url":"http://fakeimg.pl/469x220/?text=fake image 780"},{"url":"http://fakeimg.pl/233x282/?text=fake image 781"},{"url":"http://fakeimg.pl/278x321/?text=fake image 782"},{"url":"http://fakeimg.pl/214x316/?text=fake image 783"},{"url":"http://fakeimg.pl/297x239/?text=fake image 784"},{"url":"http://fakeimg.pl/474x212/?text=fake image 785"},{"url":"http://fakeimg.pl/464x251/?text=fake image 786"},{"url":"http://fakeimg.pl/496x246/?text=fake image 787"},{"url":"http://fakeimg.pl/300x321/?text=fake image 788"},{"url":"http://fakeimg.pl/246x278/?text=fake image 789"},{"url":"http://fakeimg.pl/284x308/?text=fake image 790"},{"url":"http://fakeimg.pl/313x169/?text=fake image 791"},{"url":"http://fakeimg.pl/257x298/?text=fake image 792"},{"url":"http://fakeimg.pl/303x316/?text=fake image 793"},{"url":"http://fakeimg.pl/231x190/?text=fake image 794"},{"url":"http://fakeimg.pl/490x166/?text=fake image 795"},{"url":"http://fakeimg.pl/338x332/?text=fake image 796"},{"url":"http://fakeimg.pl/443x223/?text=fake image 797"},{"url":"http://fakeimg.pl/285x200/?text=fake image 798"},{"url":"http://fakeimg.pl/424x325/?text=fake image 799"},{"url":"http://fakeimg.pl/389x285/?text=fake image 800"},{"url":"http://fakeimg.pl/214x296/?text=fake image 801"},{"url":"http://fakeimg.pl/207x251/?text=fake image 802"},{"url":"http://fakeimg.pl/223x276/?text=fake image 803"},{"url":"http://fakeimg.pl/320x300/?text=fake image 804"},{"url":"http://fakeimg.pl/344x323/?text=fake image 805"},{"url":"http://fakeimg.pl/469x197/?text=fake image 806"},{"url":"http://fakeimg.pl/392x261/?text=fake image 807"},{"url":"http://fakeimg.pl/373x271/?text=fake image 808"},{"url":"http://fakeimg.pl/353x271/?text=fake image 809"},{"url":"http://fakeimg.pl/332x217/?text=fake image 810"},{"url":"http://fakeimg.pl/390x169/?text=fake image 811"},{"url":"http://fakeimg.pl/390x286/?text=fake image 812"},{"url":"http://fakeimg.pl/466x168/?text=fake image 813"},{"url":"http://fakeimg.pl/434x201/?text=fake image 814"},{"url":"http://fakeimg.pl/289x302/?text=fake image 815"},{"url":"http://fakeimg.pl/250x248/?text=fake image 816"},{"url":"http://fakeimg.pl/456x324/?text=fake image 817"},{"url":"http://fakeimg.pl/311x324/?text=fake image 818"},{"url":"http://fakeimg.pl/386x326/?text=fake image 819"},{"url":"http://fakeimg.pl/400x191/?text=fake image 820"},{"url":"http://fakeimg.pl/428x253/?text=fake image 821"},{"url":"http://fakeimg.pl/377x214/?text=fake image 822"},{"url":"http://fakeimg.pl/438x343/?text=fake image 823"},{"url":"http://fakeimg.pl/271x339/?text=fake image 824"},{"url":"http://fakeimg.pl/468x169/?text=fake image 825"},{"url":"http://fakeimg.pl/282x177/?text=fake image 826"},{"url":"http://fakeimg.pl/333x248/?text=fake image 827"},{"url":"http://fakeimg.pl/243x296/?text=fake image 828"},{"url":"http://fakeimg.pl/253x257/?text=fake image 829"},{"url":"http://fakeimg.pl/232x280/?text=fake image 830"},{"url":"http://fakeimg.pl/349x201/?text=fake image 831"},{"url":"http://fakeimg.pl/347x227/?text=fake image 832"},{"url":"http://fakeimg.pl/202x297/?text=fake image 833"},{"url":"http://fakeimg.pl/464x323/?text=fake image 834"},{"url":"http://fakeimg.pl/381x218/?text=fake image 835"},{"url":"http://fakeimg.pl/265x337/?text=fake image 836"},{"url":"http://fakeimg.pl/346x193/?text=fake image 837"},{"url":"http://fakeimg.pl/392x345/?text=fake image 838"},{"url":"http://fakeimg.pl/444x245/?text=fake image 839"},{"url":"http://fakeimg.pl/263x256/?text=fake image 840"},{"url":"http://fakeimg.pl/352x334/?text=fake image 841"},{"url":"http://fakeimg.pl/401x233/?text=fake image 842"},{"url":"http://fakeimg.pl/463x251/?text=fake image 843"},{"url":"http://fakeimg.pl/281x196/?text=fake image 844"},{"url":"http://fakeimg.pl/361x193/?text=fake image 845"},{"url":"http://fakeimg.pl/358x343/?text=fake image 846"},{"url":"http://fakeimg.pl/360x231/?text=fake image 847"},{"url":"http://fakeimg.pl/299x316/?text=fake image 848"},{"url":"http://fakeimg.pl/381x276/?text=fake image 849"},{"url":"http://fakeimg.pl/332x217/?text=fake image 850"},{"url":"http://fakeimg.pl/445x342/?text=fake image 851"},{"url":"http://fakeimg.pl/306x166/?text=fake image 852"},{"url":"http://fakeimg.pl/483x173/?text=fake image 853"},{"url":"http://fakeimg.pl/217x222/?text=fake image 854"},{"url":"http://fakeimg.pl/235x207/?text=fake image 855"},{"url":"http://fakeimg.pl/375x292/?text=fake image 856"},{"url":"http://fakeimg.pl/273x250/?text=fake image 857"},{"url":"http://fakeimg.pl/400x244/?text=fake image 858"},{"url":"http://fakeimg.pl/380x265/?text=fake image 859"},{"url":"http://fakeimg.pl/316x216/?text=fake image 860"},{"url":"http://fakeimg.pl/396x357/?text=fake image 861"},{"url":"http://fakeimg.pl/254x259/?text=fake image 862"},{"url":"http://fakeimg.pl/362x327/?text=fake image 863"},{"url":"http://fakeimg.pl/449x332/?text=fake image 864"},{"url":"http://fakeimg.pl/494x269/?text=fake image 865"},{"url":"http://fakeimg.pl/385x286/?text=fake image 866"},{"url":"http://fakeimg.pl/221x249/?text=fake image 867"},{"url":"http://fakeimg.pl/431x320/?text=fake image 868"},{"url":"http://fakeimg.pl/469x184/?text=fake image 869"},{"url":"http://fakeimg.pl/231x347/?text=fake image 870"},{"url":"http://fakeimg.pl/209x307/?text=fake image 871"},{"url":"http://fakeimg.pl/379x178/?text=fake image 872"},{"url":"http://fakeimg.pl/238x248/?text=fake image 873"},{"url":"http://fakeimg.pl/284x202/?text=fake image 874"},{"url":"http://fakeimg.pl/217x210/?text=fake image 875"},{"url":"http://fakeimg.pl/321x231/?text=fake image 876"},{"url":"http://fakeimg.pl/354x290/?text=fake image 877"},{"url":"http://fakeimg.pl/487x203/?text=fake image 878"},{"url":"http://fakeimg.pl/361x356/?text=fake image 879"},{"url":"http://fakeimg.pl/341x161/?text=fake image 880"},{"url":"http://fakeimg.pl/327x318/?text=fake image 881"},{"url":"http://fakeimg.pl/297x253/?text=fake image 882"},{"url":"http://fakeimg.pl/280x293/?text=fake image 883"},{"url":"http://fakeimg.pl/292x222/?text=fake image 884"},{"url":"http://fakeimg.pl/267x175/?text=fake image 885"},{"url":"http://fakeimg.pl/231x270/?text=fake image 886"},{"url":"http://fakeimg.pl/491x246/?text=fake image 887"},{"url":"http://fakeimg.pl/483x281/?text=fake image 888"},{"url":"http://fakeimg.pl/462x305/?text=fake image 889"},{"url":"http://fakeimg.pl/226x238/?text=fake image 890"},{"url":"http://fakeimg.pl/269x179/?text=fake image 891"},{"url":"http://fakeimg.pl/424x234/?text=fake image 892"},{"url":"http://fakeimg.pl/487x187/?text=fake image 893"},{"url":"http://fakeimg.pl/281x278/?text=fake image 894"},{"url":"http://fakeimg.pl/300x274/?text=fake image 895"},{"url":"http://fakeimg.pl/459x239/?text=fake image 896"},{"url":"http://fakeimg.pl/274x228/?text=fake image 897"},{"url":"http://fakeimg.pl/245x309/?text=fake image 898"},{"url":"http://fakeimg.pl/234x328/?text=fake image 899"},{"url":"http://fakeimg.pl/256x255/?text=fake image 900"},{"url":"http://fakeimg.pl/268x319/?text=fake image 901"},{"url":"http://fakeimg.pl/442x295/?text=fake image 902"},{"url":"http://fakeimg.pl/456x217/?text=fake image 903"},{"url":"http://fakeimg.pl/477x318/?text=fake image 904"},{"url":"http://fakeimg.pl/272x293/?text=fake image 905"},{"url":"http://fakeimg.pl/472x306/?text=fake image 906"},{"url":"http://fakeimg.pl/398x351/?text=fake image 907"},{"url":"http://fakeimg.pl/253x161/?text=fake image 908"},{"url":"http://fakeimg.pl/269x192/?text=fake image 909"},{"url":"http://fakeimg.pl/288x190/?text=fake image 910"},{"url":"http://fakeimg.pl/411x303/?text=fake image 911"},{"url":"http://fakeimg.pl/470x319/?text=fake image 912"},{"url":"http://fakeimg.pl/333x249/?text=fake image 913"},{"url":"http://fakeimg.pl/221x209/?text=fake image 914"},{"url":"http://fakeimg.pl/445x336/?text=fake image 915"},{"url":"http://fakeimg.pl/286x269/?text=fake image 916"},{"url":"http://fakeimg.pl/307x270/?text=fake image 917"},{"url":"http://fakeimg.pl/353x241/?text=fake image 918"},{"url":"http://fakeimg.pl/356x174/?text=fake image 919"},{"url":"http://fakeimg.pl/304x177/?text=fake image 920"},{"url":"http://fakeimg.pl/231x277/?text=fake image 921"},{"url":"http://fakeimg.pl/455x307/?text=fake image 922"},{"url":"http://fakeimg.pl/284x347/?text=fake image 923"},{"url":"http://fakeimg.pl/496x208/?text=fake image 924"},{"url":"http://fakeimg.pl/317x282/?text=fake image 925"},{"url":"http://fakeimg.pl/395x334/?text=fake image 926"},{"url":"http://fakeimg.pl/281x327/?text=fake image 927"},{"url":"http://fakeimg.pl/270x186/?text=fake image 928"},{"url":"http://fakeimg.pl/245x213/?text=fake image 929"},{"url":"http://fakeimg.pl/470x220/?text=fake image 930"},{"url":"http://fakeimg.pl/346x291/?text=fake image 931"},{"url":"http://fakeimg.pl/480x252/?text=fake image 932"},{"url":"http://fakeimg.pl/471x200/?text=fake image 933"},{"url":"http://fakeimg.pl/233x342/?text=fake image 934"},{"url":"http://fakeimg.pl/476x237/?text=fake image 935"},{"url":"http://fakeimg.pl/370x277/?text=fake image 936"},{"url":"http://fakeimg.pl/374x351/?text=fake image 937"},{"url":"http://fakeimg.pl/333x221/?text=fake image 938"},{"url":"http://fakeimg.pl/401x253/?text=fake image 939"},{"url":"http://fakeimg.pl/453x350/?text=fake image 940"},{"url":"http://fakeimg.pl/269x326/?text=fake image 941"},{"url":"http://fakeimg.pl/457x280/?text=fake image 942"},{"url":"http://fakeimg.pl/468x297/?text=fake image 943"},{"url":"http://fakeimg.pl/287x265/?text=fake image 944"},{"url":"http://fakeimg.pl/483x231/?text=fake image 945"},{"url":"http://fakeimg.pl/444x343/?text=fake image 946"},{"url":"http://fakeimg.pl/263x176/?text=fake image 947"},{"url":"http://fakeimg.pl/233x295/?text=fake image 948"},{"url":"http://fakeimg.pl/374x223/?text=fake image 949"},{"url":"http://fakeimg.pl/230x215/?text=fake image 950"},{"url":"http://fakeimg.pl/308x175/?text=fake image 951"},{"url":"http://fakeimg.pl/479x294/?text=fake image 952"},{"url":"http://fakeimg.pl/335x324/?text=fake image 953"},{"url":"http://fakeimg.pl/476x353/?text=fake image 954"},{"url":"http://fakeimg.pl/285x240/?text=fake image 955"},{"url":"http://fakeimg.pl/304x219/?text=fake image 956"},{"url":"http://fakeimg.pl/347x215/?text=fake image 957"},{"url":"http://fakeimg.pl/433x328/?text=fake image 958"},{"url":"http://fakeimg.pl/351x218/?text=fake image 959"},{"url":"http://fakeimg.pl/433x279/?text=fake image 960"},{"url":"http://fakeimg.pl/231x318/?text=fake image 961"},{"url":"http://fakeimg.pl/293x199/?text=fake image 962"},{"url":"http://fakeimg.pl/390x189/?text=fake image 963"},{"url":"http://fakeimg.pl/461x178/?text=fake image 964"},{"url":"http://fakeimg.pl/333x254/?text=fake image 965"},{"url":"http://fakeimg.pl/280x165/?text=fake image 966"},{"url":"http://fakeimg.pl/210x316/?text=fake image 967"},{"url":"http://fakeimg.pl/410x230/?text=fake image 968"},{"url":"http://fakeimg.pl/360x258/?text=fake image 969"},{"url":"http://fakeimg.pl/381x235/?text=fake image 970"},{"url":"http://fakeimg.pl/398x306/?text=fake image 971"},{"url":"http://fakeimg.pl/481x164/?text=fake image 972"},{"url":"http://fakeimg.pl/432x219/?text=fake image 973"},{"url":"http://fakeimg.pl/454x321/?text=fake image 974"},{"url":"http://fakeimg.pl/268x176/?text=fake image 975"},{"url":"http://fakeimg.pl/215x234/?text=fake image 976"},{"url":"http://fakeimg.pl/456x257/?text=fake image 977"},{"url":"http://fakeimg.pl/426x322/?text=fake image 978"},{"url":"http://fakeimg.pl/235x197/?text=fake image 979"},{"url":"http://fakeimg.pl/465x200/?text=fake image 980"},{"url":"http://fakeimg.pl/324x272/?text=fake image 981"},{"url":"http://fakeimg.pl/489x163/?text=fake image 982"},{"url":"http://fakeimg.pl/409x321/?text=fake image 983"},{"url":"http://fakeimg.pl/292x295/?text=fake image 984"},{"url":"http://fakeimg.pl/482x172/?text=fake image 985"},{"url":"http://fakeimg.pl/356x280/?text=fake image 986"},{"url":"http://fakeimg.pl/374x259/?text=fake image 987"},{"url":"http://fakeimg.pl/361x232/?text=fake image 988"},{"url":"http://fakeimg.pl/222x177/?text=fake image 989"},{"url":"http://fakeimg.pl/435x165/?text=fake image 990"},{"url":"http://fakeimg.pl/304x249/?text=fake image 991"},{"url":"http://fakeimg.pl/461x218/?text=fake image 992"},{"url":"http://fakeimg.pl/430x211/?text=fake image 993"},{"url":"http://fakeimg.pl/440x332/?text=fake image 994"},{"url":"http://fakeimg.pl/324x202/?text=fake image 995"},{"url":"http://fakeimg.pl/320x200/?text=fake image 996"},{"url":"http://fakeimg.pl/430x254/?text=fake image 997"},{"url":"http://fakeimg.pl/300x324/?text=fake image 998"},{"url":"http://fakeimg.pl/276x316/?text=fake image 999"}]
